allora_sdk/__init__.py
allora_sdk/logging_config.py
allora_sdk/api_client/__init__.py
allora_sdk/api_client/client.py
allora_sdk/ml_workflow/__init__.py
allora_sdk/ml_workflow/utils.py
allora_sdk/ml_workflow/workflow.py
allora_sdk/protos/.generated.stamp
allora_sdk/protos/__init__.py
allora_sdk/protos/message_pool.py
allora_sdk/protos/amino/__init__.py
allora_sdk/protos/cosmos/__init__.py
allora_sdk/protos/cosmos/app/__init__.py
allora_sdk/protos/cosmos/app/runtime/__init__.py
allora_sdk/protos/cosmos/app/runtime/v1alpha1/__init__.py
allora_sdk/protos/cosmos/app/v1alpha1/__init__.py
allora_sdk/protos/cosmos/auth/__init__.py
allora_sdk/protos/cosmos/auth/module/__init__.py
allora_sdk/protos/cosmos/auth/module/v1/__init__.py
allora_sdk/protos/cosmos/auth/v1beta1/__init__.py
allora_sdk/protos/cosmos/authz/__init__.py
allora_sdk/protos/cosmos/authz/module/__init__.py
allora_sdk/protos/cosmos/authz/module/v1/__init__.py
allora_sdk/protos/cosmos/authz/v1beta1/__init__.py
allora_sdk/protos/cosmos/autocli/__init__.py
allora_sdk/protos/cosmos/autocli/v1/__init__.py
allora_sdk/protos/cosmos/bank/__init__.py
allora_sdk/protos/cosmos/bank/module/__init__.py
allora_sdk/protos/cosmos/bank/module/v1/__init__.py
allora_sdk/protos/cosmos/bank/v1beta1/__init__.py
allora_sdk/protos/cosmos/base/__init__.py
allora_sdk/protos/cosmos/base/abci/__init__.py
allora_sdk/protos/cosmos/base/abci/v1beta1/__init__.py
allora_sdk/protos/cosmos/base/node/__init__.py
allora_sdk/protos/cosmos/base/node/v1beta1/__init__.py
allora_sdk/protos/cosmos/base/query/__init__.py
allora_sdk/protos/cosmos/base/query/v1beta1/__init__.py
allora_sdk/protos/cosmos/base/reflection/__init__.py
allora_sdk/protos/cosmos/base/reflection/v1beta1/__init__.py
allora_sdk/protos/cosmos/base/reflection/v2alpha1/__init__.py
allora_sdk/protos/cosmos/base/tendermint/__init__.py
allora_sdk/protos/cosmos/base/tendermint/v1beta1/__init__.py
allora_sdk/protos/cosmos/base/v1beta1/__init__.py
allora_sdk-1.0.6.dist-info/METADATA
allora_sdk-1.0.6.dist-info/WHEEL
allora_sdk-1.0.6.dist-info/entry_points.txt
allora_sdk-1.0.6.dist-info/licenses/LICENSE
allora_sdk-1.0.6.dist-info/RECORD
