Metadata-Version: 2.4
Name: allora_sdk
Version: 1.0.6
Summary: Allora Network SDK
Project-URL: Homepage, https://github.com/allora-network/allora-sdk-py
Project-URL: Issues, https://github.com/allora-network/allora-sdk-py/issues
Project-URL: Allora Network, https://allora.network
Author-email: spooktheducks <spook@alloralabs.xyz>, gh-allora <gregory@alloralabs.xyz>, jefferythewind <tim@alloralabs.xyz>
License-File: LICENSE
Classifier: License :: OSI Approved :: Apache Software License
Classifier: Operating System :: OS Independent
Classifier: Programming Language :: Python :: 3
Classifier: Programming Language :: Python :: 3 :: Only
Classifier: Programming Language :: Python :: 3.10
Classifier: Programming Language :: Python :: 3.11
Classifier: Programming Language :: Python :: 3.12
Classifier: Programming Language :: Python :: 3.13
Requires-Python: >=3.10
Requires-Dist: aiohttp~=3.12
Requires-Dist: async-timeout>=5.0.1
Requires-Dist: betterproto2~=0.7.0
Requires-Dist: cosmpy>=0.11.1
Requires-Dist: dill
Requires-Dist: grpclib>=0.4.8
Requires-Dist: hdwallets>=0.1.2
Requires-Dist: lightgbm
Requires-Dist: matplotlib
Requires-Dist: mnemonic>=0.21
Requires-Dist: numpy
Requires-Dist: pandas
Requires-Dist: pydantic>=2.10.4
Requires-Dist: requests
Requires-Dist: requests~=2.32
Requires-Dist: websockets>=15.0.1
Provides-Extra: codegen
Requires-Dist: betterproto2-compiler; extra == 'codegen'
Requires-Dist: grpcio-tools; extra == 'codegen'
Requires-Dist: openapi-python-client; extra == 'codegen'
Requires-Dist: pyyaml; extra == 'codegen'
Provides-Extra: dev
Requires-Dist: fastapi; extra == 'dev'
Requires-Dist: httpx; extra == 'dev'
Requires-Dist: mypy==1.11.2; extra == 'dev'
Requires-Dist: pytest-asyncio>=1.1.0; extra == 'dev'
Requires-Dist: pytest-timeout>=2.4.0; extra == 'dev'
Requires-Dist: pytest>=8.4.1; extra == 'dev'
Requires-Dist: starlette; extra == 'dev'
Requires-Dist: tox; extra == 'dev'
Requires-Dist: types-cachetools>=5.5.0.20240820; extra == 'dev'
Requires-Dist: types-chardet>=5.0.4.6; extra == 'dev'
